[
    {
        "title": "01. Introduction",
        "link1": {
            "linkName": "History",
            "link": "https://github.com/rcos/CSCI-4470-OpenSource/tree/master/Modules/01.Introduction/History"
        },
        "link2": {
            "linkName": "Linux",
            "link": "https://github.com/rcos/CSCI-4470-OpenSource/tree/master/Modules/01.Introduction/Linux"
        },
        "link3": {
            "linkName": "Lab 01 (in class lab)"
            // There should have a link to the Lab 01 hand out
        }
    },
    {
        "title": "02. Git",
        "link1": {
            "linkName": "Git Introduction Part 1",
            "link": "../../../Modules/02.Git/Git-Introduction-Part-I/index.html"
        },
        "link2": {
            "linkName": "Git Introduction Part 2",
            "link": "../../../Modules/02.Git/Git-Introduction-Part-II/index.html"
        },
        "link3": {
            "linkName": "Git Cheat Sheet",
            "link": "../../../Modules/02.Git/cheat_sheet_git_final.pdf"
        }
    },
    {
        "title": "03.Documentation And Community",
        "link1": {
            "linkName": "Documentation",
            "link": "../../../Modules/03.DocumentationAndCommunity/Documentation.html"
        },
        "link2": {
            "linkName": "Community",
            "link": "../../../Modules/03.DocumentationAndCommunity/Community.html"
        },
        "link3": {
            "linkName": "Lab",
            "link": "https://github.com/rcos/CSCI-4470-OpenSource/blob/master/Modules/03.DocumentationAndCommunity/Lab-DocumentationAndCommunity.md"
        }
    },
    {
        "title": "04. Licensing" 
    },
    {
        "title": "05. Build System"
    },
    {
        "title": "06. Scientific Computing" 
    },
    {
        "title": "07. Statistical Computing" 
    },
    {
        "title": "08. Testing And CI" 
    },
    {
        "title": "09. Virtualization" 
    },
    {
        "title": "10. Databases" 
    },
    {
        "title": "11. Tensorflow"
    }
]